meerkat/__init__.py
meerkat/det2lab_xds.py
meerkat/meerkat.py
meerkat-0.3.9.dist-info/LICENSE
meerkat-0.3.9.dist-info/METADATA
meerkat-0.3.9.dist-info/WHEEL
meerkat-0.3.9.dist-info/top_level.txt
meerkat-0.3.9.dist-info/RECORD
