Metadata-Version: 2.1
Name: meerkat
Version: 0.3.9
Summary: A program for reciprocal space reconstruction
Author: Dmitry Logvinovich
Author-email: Arkadiy Simonov <aglietto@gmail.com>
Project-URL: Homepage, https://github.com/aglie/meerkat.git
Keywords: crystallography,single crystal,reciprocal space reconstruction
License-File: LICENSE
Requires-Dist: fabio
Requires-Dist: h5py
Requires-Dist: numpy
